promptart/__init__.py
promptart/__main__.py
promptart/_version.py
promptart/app.py
promptart/authentication.py
promptart/constants.py
promptart/gallery.py
promptart/image_generation.py
promptart/logo.py
promptart/speech_generation.py
promptart-0.2.0.dist-info/METADATA
promptart-0.2.0.dist-info/WHEEL
promptart-0.2.0.dist-info/entry_points.txt
promptart-0.2.0.dist-info/licenses/LICENSE
promptart-0.2.0.dist-info/RECORD
